[
    {
        "expand": "description,lead,issueTypes,url,projectKeys,permissions,insight",
        "self": "https:\/\/francemm.atlassian.net\/rest\/api\/2\/project\/10008",
        "id": "10008",
        "key": "APPS",
        "name": "Applications",
        "avatarUrls": {
            "48x48": "https:\/\/francemm.atlassian.net\/secure\/projectavatar?pid=10008&avatarId=10404",
            "24x24": "https:\/\/francemm.atlassian.net\/secure\/projectavatar?size=small&s=small&pid=10008&avatarId=10404",
            "16x16": "https:\/\/francemm.atlassian.net\/secure\/projectavatar?size=xsmall&s=xsmall&pid=10008&avatarId=10404",
            "32x32": "https:\/\/francemm.atlassian.net\/secure\/projectavatar?size=medium&s=medium&pid=10008&avatarId=10404"
        },
        "projectTypeKey": "software",
        "simplified": true,
        "style": "next-gen",
        "isPrivate": false,
        "properties": [],
        "entityId": "08afaa01-af6f-4dd4-bcf3-38bba5d2c85c",
        "uuid": "08afaa01-af6f-4dd4-bcf3-38bba5d2c85c"
    },
    {
        "expand": "description,lead,issueTypes,url,projectKeys,permissions,insight",
        "self": "https:\/\/francemm.atlassian.net\/rest\/api\/2\/project\/10027",
        "id": "10027",
        "key": "BAC",
        "name": "Bach",
        "avatarUrls": {
            "48x48": "https:\/\/francemm.atlassian.net\/secure\/projectavatar?pid=10027&avatarId=10561",
            "24x24": "https:\/\/francemm.atlassian.net\/secure\/projectavatar?size=small&s=small&pid=10027&avatarId=10561",
            "16x16": "https:\/\/francemm.atlassian.net\/secure\/projectavatar?size=xsmall&s=xsmall&pid=10027&avatarId=10561",
            "32x32": "https:\/\/francemm.atlassian.net\/secure\/projectavatar?size=medium&s=medium&pid=10027&avatarId=10561"
        },
        "projectTypeKey": "software",
        "simplified": false,
        "style": "classic",
        "isPrivate": false,
        "properties": []
    },
    {
        "expand": "description,lead,issueTypes,url,projectKeys,permissions,insight",
        "self": "https:\/\/francemm.atlassian.net\/rest\/api\/2\/project\/10004",
        "id": "10004",
        "key": "BACH2",
        "name": "Bach source",
        "avatarUrls": {
            "48x48": "https:\/\/francemm.atlassian.net\/secure\/projectavatar?pid=10004&avatarId=10555",
            "24x24": "https:\/\/francemm.atlassian.net\/secure\/projectavatar?size=small&s=small&pid=10004&avatarId=10555",
            "16x16": "https:\/\/francemm.atlassian.net\/secure\/projectavatar?size=xsmall&s=xsmall&pid=10004&avatarId=10555",
            "32x32": "https:\/\/francemm.atlassian.net\/secure\/projectavatar?size=medium&s=medium&pid=10004&avatarId=10555"
        },
        "projectTypeKey": "software",
        "simplified": true,
        "style": "next-gen",
        "isPrivate": false,
        "properties": [],
        "entityId": "7d829204-53f7-4292-8a3d-0d405c77c72d",
        "uuid": "7d829204-53f7-4292-8a3d-0d405c77c72d"
    },
    {
        "expand": "description,lead,issueTypes,url,projectKeys,permissions,insight",
        "self": "https:\/\/francemm.atlassian.net\/rest\/api\/2\/project\/10014",
        "id": "10014",
        "key": "BTF",
        "name": "Board t\u00e2ches FMM",
        "avatarUrls": {
            "48x48": "https:\/\/francemm.atlassian.net\/secure\/projectavatar?pid=10014&avatarId=10410",
            "24x24": "https:\/\/francemm.atlassian.net\/secure\/projectavatar?size=small&s=small&pid=10014&avatarId=10410",
            "16x16": "https:\/\/francemm.atlassian.net\/secure\/projectavatar?size=xsmall&s=xsmall&pid=10014&avatarId=10410",
            "32x32": "https:\/\/francemm.atlassian.net\/secure\/projectavatar?size=medium&s=medium&pid=10014&avatarId=10410"
        },
        "projectTypeKey": "software",
        "simplified": true,
        "style": "next-gen",
        "isPrivate": true,
        "properties": [],
        "entityId": "76e0d959-1ac0-45fb-8b06-2cb0eed4d22f",
        "uuid": "76e0d959-1ac0-45fb-8b06-2cb0eed4d22f"
    },
    {
        "expand": "description,lead,issueTypes,url,projectKeys,permissions,insight",
        "self": "https:\/\/francemm.atlassian.net\/rest\/api\/2\/project\/10021",
        "id": "10021",
        "key": "EXPBT",
        "name": "EXP\/BT",
        "avatarUrls": {
            "48x48": "https:\/\/francemm.atlassian.net\/secure\/projectavatar?pid=10021&avatarId=10401",
            "24x24": "https:\/\/francemm.atlassian.net\/secure\/projectavatar?size=small&s=small&pid=10021&avatarId=10401",
            "16x16": "https:\/\/francemm.atlassian.net\/secure\/projectavatar?size=xsmall&s=xsmall&pid=10021&avatarId=10401",
            "32x32": "https:\/\/francemm.atlassian.net\/secure\/projectavatar?size=medium&s=medium&pid=10021&avatarId=10401"
        },
        "projectTypeKey": "software",
        "simplified": false,
        "style": "classic",
        "isPrivate": false,
        "properties": []
    },
    {
        "expand": "description,lead,issueTypes,url,projectKeys,permissions,insight",
        "self": "https:\/\/francemm.atlassian.net\/rest\/api\/2\/project\/10020",
        "id": "10020",
        "key": "FV",
        "name": "FOV",
        "avatarUrls": {
            "48x48": "https:\/\/francemm.atlassian.net\/secure\/projectavatar?pid=10020&avatarId=10556",
            "24x24": "https:\/\/francemm.atlassian.net\/secure\/projectavatar?size=small&s=small&pid=10020&avatarId=10556",
            "16x16": "https:\/\/francemm.atlassian.net\/secure\/projectavatar?size=xsmall&s=xsmall&pid=10020&avatarId=10556",
            "32x32": "https:\/\/francemm.atlassian.net\/secure\/projectavatar?size=medium&s=medium&pid=10020&avatarId=10556"
        },
        "projectTypeKey": "software",
        "simplified": false,
        "style": "classic",
        "isPrivate": false,
        "properties": []
    },
    {
        "expand": "description,lead,issueTypes,url,projectKeys,permissions,insight",
        "self": "https:\/\/francemm.atlassian.net\/rest\/api\/2\/project\/10016",
        "id": "10016",
        "key": "OLDAM",
        "name": "Imports Trello APPs",
        "avatarUrls": {
            "48x48": "https:\/\/francemm.atlassian.net\/secure\/projectavatar?pid=10016&avatarId=10422",
            "24x24": "https:\/\/francemm.atlassian.net\/secure\/projectavatar?size=small&s=small&pid=10016&avatarId=10422",
            "16x16": "https:\/\/francemm.atlassian.net\/secure\/projectavatar?size=xsmall&s=xsmall&pid=10016&avatarId=10422",
            "32x32": "https:\/\/francemm.atlassian.net\/secure\/projectavatar?size=medium&s=medium&pid=10016&avatarId=10422"
        },
        "projectTypeKey": "software",
        "simplified": true,
        "style": "next-gen",
        "isPrivate": false,
        "properties": [],
        "entityId": "8c41f45c-8b95-464a-afa4-da7a1b0d4cc5",
        "uuid": "8c41f45c-8b95-464a-afa4-da7a1b0d4cc5"
    },
    {
        "expand": "description,lead,issueTypes,url,projectKeys,permissions,insight",
        "self": "https:\/\/francemm.atlassian.net\/rest\/api\/2\/project\/10024",
        "id": "10024",
        "key": "IN",
        "name": "Infomigrants",
        "avatarUrls": {
            "48x48": "https:\/\/francemm.atlassian.net\/secure\/projectavatar?pid=10024&avatarId=10410",
            "24x24": "https:\/\/francemm.atlassian.net\/secure\/projectavatar?size=small&s=small&pid=10024&avatarId=10410",
            "16x16": "https:\/\/francemm.atlassian.net\/secure\/projectavatar?size=xsmall&s=xsmall&pid=10024&avatarId=10410",
            "32x32": "https:\/\/francemm.atlassian.net\/secure\/projectavatar?size=medium&s=medium&pid=10024&avatarId=10410"
        },
        "projectTypeKey": "software",
        "simplified": false,
        "style": "classic",
        "isPrivate": false,
        "properties": []
    },
    {
        "expand": "description,lead,issueTypes,url,projectKeys,permissions,insight",
        "self": "https:\/\/francemm.atlassian.net\/rest\/api\/2\/project\/10009",
        "id": "10009",
        "key": "MIGROO",
        "name": "Infomigrants V0",
        "avatarUrls": {
            "48x48": "https:\/\/francemm.atlassian.net\/secure\/projectavatar?pid=10009&avatarId=10406",
            "24x24": "https:\/\/francemm.atlassian.net\/secure\/projectavatar?size=small&s=small&pid=10009&avatarId=10406",
            "16x16": "https:\/\/francemm.atlassian.net\/secure\/projectavatar?size=xsmall&s=xsmall&pid=10009&avatarId=10406",
            "32x32": "https:\/\/francemm.atlassian.net\/secure\/projectavatar?size=medium&s=medium&pid=10009&avatarId=10406"
        },
        "projectTypeKey": "software",
        "simplified": true,
        "style": "next-gen",
        "isPrivate": false,
        "properties": [],
        "entityId": "021ec37f-7de1-4632-a114-a532b0e11f7b",
        "uuid": "021ec37f-7de1-4632-a114-a532b0e11f7b"
    },
    {
        "expand": "description,lead,issueTypes,url,projectKeys,permissions,insight",
        "self": "https:\/\/francemm.atlassian.net\/rest\/api\/2\/project\/10025",
        "id": "10025",
        "key": "INNO",
        "name": "INNO",
        "avatarUrls": {
            "48x48": "https:\/\/francemm.atlassian.net\/secure\/projectavatar?pid=10025&avatarId=10411",
            "24x24": "https:\/\/francemm.atlassian.net\/secure\/projectavatar?size=small&s=small&pid=10025&avatarId=10411",
            "16x16": "https:\/\/francemm.atlassian.net\/secure\/projectavatar?size=xsmall&s=xsmall&pid=10025&avatarId=10411",
            "32x32": "https:\/\/francemm.atlassian.net\/secure\/projectavatar?size=medium&s=medium&pid=10025&avatarId=10411"
        },
        "projectTypeKey": "software",
        "simplified": false,
        "style": "classic",
        "isPrivate": false,
        "properties": []
    },
    {
        "expand": "description,lead,issueTypes,url,projectKeys,permissions,insight",
        "self": "https:\/\/francemm.atlassian.net\/rest\/api\/2\/project\/10007",
        "id": "10007",
        "key": "MEZZO",
        "name": "MEZZO",
        "avatarUrls": {
            "48x48": "https:\/\/francemm.atlassian.net\/secure\/projectavatar?pid=10007&avatarId=10562",
            "24x24": "https:\/\/francemm.atlassian.net\/secure\/projectavatar?size=small&s=small&pid=10007&avatarId=10562",
            "16x16": "https:\/\/francemm.atlassian.net\/secure\/projectavatar?size=xsmall&s=xsmall&pid=10007&avatarId=10562",
            "32x32": "https:\/\/francemm.atlassian.net\/secure\/projectavatar?size=medium&s=medium&pid=10007&avatarId=10562"
        },
        "projectTypeKey": "software",
        "simplified": false,
        "style": "classic",
        "isPrivate": false,
        "properties": []
    },
    {
        "expand": "description,lead,issueTypes,url,projectKeys,permissions,insight",
        "self": "https:\/\/francemm.atlassian.net\/rest\/api\/2\/project\/10032",
        "id": "10032",
        "key": "MJEC",
        "name": "Migration Jira et Confluence",
        "avatarUrls": {
            "48x48": "https:\/\/francemm.atlassian.net\/secure\/projectavatar?pid=10032&avatarId=10414",
            "24x24": "https:\/\/francemm.atlassian.net\/secure\/projectavatar?size=small&s=small&pid=10032&avatarId=10414",
            "16x16": "https:\/\/francemm.atlassian.net\/secure\/projectavatar?size=xsmall&s=xsmall&pid=10032&avatarId=10414",
            "32x32": "https:\/\/francemm.atlassian.net\/secure\/projectavatar?size=medium&s=medium&pid=10032&avatarId=10414"
        },
        "projectTypeKey": "software",
        "simplified": true,
        "style": "next-gen",
        "isPrivate": false,
        "properties": [],
        "entityId": "b94930d4-de16-40ac-9e54-fa9b99504e75",
        "uuid": "b94930d4-de16-40ac-9e54-fa9b99504e75"
    },
    {
        "expand": "description,lead,issueTypes,url,projectKeys,permissions,insight",
        "self": "https:\/\/francemm.atlassian.net\/rest\/api\/2\/project\/10030",
        "id": "10030",
        "key": "MDA",
        "name": "Mon\u00e9tisation des audios",
        "avatarUrls": {
            "48x48": "https:\/\/francemm.atlassian.net\/secure\/projectavatar?pid=10030&avatarId=10414",
            "24x24": "https:\/\/francemm.atlassian.net\/secure\/projectavatar?size=small&s=small&pid=10030&avatarId=10414",
            "16x16": "https:\/\/francemm.atlassian.net\/secure\/projectavatar?size=xsmall&s=xsmall&pid=10030&avatarId=10414",
            "32x32": "https:\/\/francemm.atlassian.net\/secure\/projectavatar?size=medium&s=medium&pid=10030&avatarId=10414"
        },
        "projectTypeKey": "software",
        "simplified": false,
        "style": "classic",
        "isPrivate": false,
        "properties": []
    },
    {
        "expand": "description,lead,issueTypes,url,projectKeys,permissions,insight",
        "self": "https:\/\/francemm.atlassian.net\/rest\/api\/2\/project\/10006",
        "id": "10006",
        "key": "ONFMM",
        "name": "Onboarding FMM",
        "avatarUrls": {
            "48x48": "https:\/\/francemm.atlassian.net\/secure\/projectavatar?pid=10006&avatarId=10419",
            "24x24": "https:\/\/francemm.atlassian.net\/secure\/projectavatar?size=small&s=small&pid=10006&avatarId=10419",
            "16x16": "https:\/\/francemm.atlassian.net\/secure\/projectavatar?size=xsmall&s=xsmall&pid=10006&avatarId=10419",
            "32x32": "https:\/\/francemm.atlassian.net\/secure\/projectavatar?size=medium&s=medium&pid=10006&avatarId=10419"
        },
        "projectTypeKey": "software",
        "simplified": false,
        "style": "classic",
        "isPrivate": false,
        "properties": []
    },
    {
        "expand": "description,lead,issueTypes,url,projectKeys,permissions,insight",
        "self": "https:\/\/francemm.atlassian.net\/rest\/api\/2\/project\/10019",
        "id": "10019",
        "key": "OP",
        "name": "Op\u00e9ra",
        "avatarUrls": {
            "48x48": "https:\/\/francemm.atlassian.net\/secure\/projectavatar?pid=10019&avatarId=10560",
            "24x24": "https:\/\/francemm.atlassian.net\/secure\/projectavatar?size=small&s=small&pid=10019&avatarId=10560",
            "16x16": "https:\/\/francemm.atlassian.net\/secure\/projectavatar?size=xsmall&s=xsmall&pid=10019&avatarId=10560",
            "32x32": "https:\/\/francemm.atlassian.net\/secure\/projectavatar?size=medium&s=medium&pid=10019&avatarId=10560"
        },
        "projectTypeKey": "software",
        "simplified": false,
        "style": "classic",
        "isPrivate": false,
        "properties": []
    },
    {
        "expand": "description,lead,issueTypes,url,projectKeys,permissions,insight",
        "self": "https:\/\/francemm.atlassian.net\/rest\/api\/2\/project\/10023",
        "id": "10023",
        "key": "SP",
        "name": "Suivi Performance",
        "avatarUrls": {
            "48x48": "https:\/\/francemm.atlassian.net\/secure\/projectavatar?pid=10023&avatarId=10421",
            "24x24": "https:\/\/francemm.atlassian.net\/secure\/projectavatar?size=small&s=small&pid=10023&avatarId=10421",
            "16x16": "https:\/\/francemm.atlassian.net\/secure\/projectavatar?size=xsmall&s=xsmall&pid=10023&avatarId=10421",
            "32x32": "https:\/\/francemm.atlassian.net\/secure\/projectavatar?size=medium&s=medium&pid=10023&avatarId=10421"
        },
        "projectTypeKey": "software",
        "simplified": true,
        "style": "next-gen",
        "isPrivate": false,
        "properties": [],
        "entityId": "6432d68c-7a09-45ca-9e18-e14811b4a75a",
        "uuid": "6432d68c-7a09-45ca-9e18-e14811b4a75a"
    },
    {
        "expand": "description,lead,issueTypes,url,projectKeys,permissions,insight",
        "self": "https:\/\/francemm.atlassian.net\/rest\/api\/2\/project\/10015",
        "id": "10015",
        "key": "TCAP",
        "name": "TCap",
        "avatarUrls": {
            "48x48": "https:\/\/francemm.atlassian.net\/secure\/projectavatar?pid=10015&avatarId=10410",
            "24x24": "https:\/\/francemm.atlassian.net\/secure\/projectavatar?size=small&s=small&pid=10015&avatarId=10410",
            "16x16": "https:\/\/francemm.atlassian.net\/secure\/projectavatar?size=xsmall&s=xsmall&pid=10015&avatarId=10410",
            "32x32": "https:\/\/francemm.atlassian.net\/secure\/projectavatar?size=medium&s=medium&pid=10015&avatarId=10410"
        },
        "projectTypeKey": "software",
        "simplified": true,
        "style": "next-gen",
        "isPrivate": true,
        "properties": [],
        "entityId": "8f15e32d-59bf-4248-86c2-610e910a33e9",
        "uuid": "8f15e32d-59bf-4248-86c2-610e910a33e9"
    },
    {
        "expand": "description,lead,issueTypes,url,projectKeys,permissions,insight",
        "self": "https:\/\/francemm.atlassian.net\/rest\/api\/2\/project\/10022",
        "id": "10022",
        "key": "TK",
        "name": "Test Kanban",
        "avatarUrls": {
            "48x48": "https:\/\/francemm.atlassian.net\/secure\/projectavatar?pid=10022&avatarId=10425",
            "24x24": "https:\/\/francemm.atlassian.net\/secure\/projectavatar?size=small&s=small&pid=10022&avatarId=10425",
            "16x16": "https:\/\/francemm.atlassian.net\/secure\/projectavatar?size=xsmall&s=xsmall&pid=10022&avatarId=10425",
            "32x32": "https:\/\/francemm.atlassian.net\/secure\/projectavatar?size=medium&s=medium&pid=10022&avatarId=10425"
        },
        "projectTypeKey": "software",
        "simplified": false,
        "style": "classic",
        "isPrivate": false,
        "properties": []
    },
    {
        "expand": "description,lead,issueTypes,url,projectKeys,permissions,insight",
        "self": "https:\/\/francemm.atlassian.net\/rest\/api\/2\/project\/10017",
        "id": "10017",
        "key": "TW",
        "name": "Test WF",
        "avatarUrls": {
            "48x48": "https:\/\/francemm.atlassian.net\/secure\/projectavatar?pid=10017&avatarId=10408",
            "24x24": "https:\/\/francemm.atlassian.net\/secure\/projectavatar?size=small&s=small&pid=10017&avatarId=10408",
            "16x16": "https:\/\/francemm.atlassian.net\/secure\/projectavatar?size=xsmall&s=xsmall&pid=10017&avatarId=10408",
            "32x32": "https:\/\/francemm.atlassian.net\/secure\/projectavatar?size=medium&s=medium&pid=10017&avatarId=10408"
        },
        "projectTypeKey": "software",
        "simplified": false,
        "style": "classic",
        "isPrivate": false,
        "properties": []
    },
    {
        "expand": "description,lead,issueTypes,url,projectKeys,permissions,insight",
        "self": "https:\/\/francemm.atlassian.net\/rest\/api\/2\/project\/10018",
        "id": "10018",
        "key": "TNG",
        "name": "Test WFNG",
        "avatarUrls": {
            "48x48": "https:\/\/francemm.atlassian.net\/secure\/projectavatar?pid=10018&avatarId=10401",
            "24x24": "https:\/\/francemm.atlassian.net\/secure\/projectavatar?size=small&s=small&pid=10018&avatarId=10401",
            "16x16": "https:\/\/francemm.atlassian.net\/secure\/projectavatar?size=xsmall&s=xsmall&pid=10018&avatarId=10401",
            "32x32": "https:\/\/francemm.atlassian.net\/secure\/projectavatar?size=medium&s=medium&pid=10018&avatarId=10401"
        },
        "projectTypeKey": "software",
        "simplified": true,
        "style": "next-gen",
        "isPrivate": true,
        "properties": [],
        "entityId": "e2b65957-eadc-4341-80b5-da7a6bf224e0",
        "uuid": "e2b65957-eadc-4341-80b5-da7a6bf224e0"
    },
    {
        "expand": "description,lead,issueTypes,url,projectKeys,permissions,insight",
        "self": "https:\/\/francemm.atlassian.net\/rest\/api\/2\/project\/10031",
        "id": "10031",
        "key": "TJJ",
        "name": "test-jenkins-jira",
        "avatarUrls": {
            "48x48": "https:\/\/francemm.atlassian.net\/secure\/projectavatar?pid=10031&avatarId=10407",
            "24x24": "https:\/\/francemm.atlassian.net\/secure\/projectavatar?size=small&s=small&pid=10031&avatarId=10407",
            "16x16": "https:\/\/francemm.atlassian.net\/secure\/projectavatar?size=xsmall&s=xsmall&pid=10031&avatarId=10407",
            "32x32": "https:\/\/francemm.atlassian.net\/secure\/projectavatar?size=medium&s=medium&pid=10031&avatarId=10407"
        },
        "projectTypeKey": "software",
        "simplified": true,
        "style": "next-gen",
        "isPrivate": false,
        "properties": [],
        "entityId": "bf284dca-1bf5-4eef-91c2-56c83a2f1e65",
        "uuid": "bf284dca-1bf5-4eef-91c2-56c83a2f1e65"
    }
]
